LICENSE
dg_commons/__init__.py
dg_commons/controllers/__init__.py
dg_commons/controllers/pid.py
dg_commons/controllers/pure_pursuit.py
dg_commons/controllers/speed.py
dg_commons/controllers/steer.py
dg_commons/dynamics/__init__.py
dg_commons/dynamics/bicycle_dynamic.py
dg_commons/game_types.py
dg_commons/geo.py
dg_commons/index.rst
dg_commons/maps/__init__.py
dg_commons/maps/lanes.py
dg_commons/maps/road_bounds.py
dg_commons/maps/shapely_viz.py
dg_commons/maps/shapes_generator.py
dg_commons/perception/__init__.py
dg_commons/perception/sensor.py
dg_commons/planning/__init__.py
dg_commons/planning/commands_sampler.py
dg_commons/planning/motion_primitives.py
dg_commons/planning/trajectory.py
dg_commons/planning/trajectory_generator_abc.py
dg_commons/seq/__init__.py
dg_commons/seq/seq_op.py
dg_commons/seq/sequence.py
dg_commons/sim/__init__.py
dg_commons/sim/agents/__init__.py
dg_commons/sim/agents/agent.py
dg_commons/sim/agents/lane_follower.py
dg_commons/sim/collision.py
dg_commons/sim/collision_structures.py
dg_commons/sim/collision_utils.py
dg_commons/sim/collision_visualisation.py
dg_commons/sim/goals.py
dg_commons/sim/index.rst
dg_commons/sim/log_visualisation.py
dg_commons/sim/models/__init__.py
dg_commons/sim/models/diff_drive.py
dg_commons/sim/models/diff_drive_structures.py
dg_commons/sim/models/model_structures.py
dg_commons/sim/models/model_utils.py
dg_commons/sim/models/obstacles.py
dg_commons/sim/models/obstacles_dyn.py
dg_commons/sim/models/pedestrian.py
dg_commons/sim/models/pedestrian_utils.py
dg_commons/sim/models/rocket.py
dg_commons/sim/models/rocket_structures.py
dg_commons/sim/models/spacecraft.py
dg_commons/sim/models/spacecraft_structures.py
dg_commons/sim/models/tires.py
dg_commons/sim/models/utils.py
dg_commons/sim/models/vehicle.py
dg_commons/sim/models/vehicle_dynamic.py
dg_commons/sim/models/vehicle_ligths.py
dg_commons/sim/models/vehicle_structures.py
dg_commons/sim/models/vehicle_utils.py
dg_commons/sim/scenarios/__init__.py
dg_commons-0.0.47.dist-info/LICENSE
dg_commons-0.0.47.dist-info/METADATA
dg_commons-0.0.47.dist-info/WHEEL
dg_commons-0.0.47.dist-info/RECORD
