Metadata-Version: 2.1
Name: dg-commons
Version: 0.0.47
Summary: Common tools and utilities related to Driving Games
Home-page: https://github.com/idsc-frazzoli/dg-commons
License: LICENSE
Author: Alessandro Zanardi
Author-email: azanardi@ethz.ch
Requires-Python: >=3.9,<4.0
Classifier: Development Status :: 3 - Alpha
Classifier: License :: OSI Approved :: GNU General Public License v3 (GPLv3)
Classifier: License :: Other/Proprietary License
Classifier: Programming Language :: Python :: 3
Classifier: Programming Language :: Python :: 3.9
Classifier: Programming Language :: Python :: 3.10
Classifier: Programming Language :: Python :: 3.11
Classifier: Programming Language :: Python :: 3.12
Requires-Dist: PyGeometry-z7 (==7.2)
Requires-Dist: aiofiles
Requires-Dist: cachetools (>=5.0.0,<6.0.0)
Requires-Dist: commonroad-drivability-checker (==2024.1)
Requires-Dist: commonroad-io (==2024.1)
Requires-Dist: cytoolz (>=0.12.0,<0.13.0)
Requires-Dist: frozendict (>=2.3.4,<3.0.0)
Requires-Dist: future
Requires-Dist: matplotlib (<3.9.0)
Requires-Dist: numpy (>=1.21.2,<2.0.0)
Requires-Dist: pycontracts3 (==7.2)
Requires-Dist: pytz
Requires-Dist: scipy (>=1.8.0,<2.0.0)
Requires-Dist: shapely (>=2.0.0,<3.0.0)
Requires-Dist: tqdm (>=4.62.3,<5.0.0)
Requires-Dist: webcolors
Requires-Dist: xtermcolor
Requires-Dist: zuper-commons-z7 (==7.2)
Project-URL: Repository, https://github.com/idsc-frazzoli/dg-commons
